hybrid_model_for_russian_sentiment_analysis/__init__.py
hybrid_model_for_russian_sentiment_analysis/model.py
hybrid_model_for_russian_sentiment_analysis/config/config.yaml
hybrid_model_for_russian_sentiment_analysis/constants/__init__.py
hybrid_model_for_russian_sentiment_analysis/entity/__init__.py
hybrid_model_for_russian_sentiment_analysis/entity/dataset.py
hybrid_model_for_russian_sentiment_analysis/models/__init__.py
hybrid_model_for_russian_sentiment_analysis/models/attention.py
hybrid_model_for_russian_sentiment_analysis/models/convolutional.py
hybrid_model_for_russian_sentiment_analysis/models/head.py
hybrid_model_for_russian_sentiment_analysis/models/linear.py
hybrid_model_for_russian_sentiment_analysis/models/recurrent.py
hybrid_model_for_russian_sentiment_analysis/models/trio.py
hybrid_model_for_russian_sentiment_analysis/params/head_model_FINAL_MHSA_STCNN_BiLSTM.yaml
hybrid_model_for_russian_sentiment_analysis/params/head_model_FINAL_MHSA_STCNN_BiRNN.yaml
hybrid_model_for_russian_sentiment_analysis/params/head_model_FINAL_MHSA_STCNN_GRU.yaml
hybrid_model_for_russian_sentiment_analysis/utils/__init__.py
hybrid_model_for_russian_sentiment_analysis/utils/common.py
hybrid_model_for_russian_sentiment_analysis-1.0.2.dist-info/LICENSE.txt
hybrid_model_for_russian_sentiment_analysis-1.0.2.dist-info/METADATA
hybrid_model_for_russian_sentiment_analysis-1.0.2.dist-info/WHEEL
hybrid_model_for_russian_sentiment_analysis-1.0.2.dist-info/dependency_links.txt
hybrid_model_for_russian_sentiment_analysis-1.0.2.dist-info/top_level.txt
hybrid_model_for_russian_sentiment_analysis-1.0.2.dist-info/RECORD
