Metadata-Version: 2.1
Name: hybrid-model-for-russian-sentiment-analysis
Version: 1.0.2
Summary: Hybrid Model for detecting sensitive content in textual Russian news feeds
Home-page: https://github.com/GitHub-User228/hybrid_model_for_russian_sentiment_analysis
Author: GitHub-User228
Author-email: egor.udalov13@gmail.com
License: UNKNOWN
Platform: UNKNOWN
Classifier: Programming Language :: Python :: 3
Classifier: License :: OSI Approved :: MIT License
Classifier: Operating System :: OS Independent
Requires-Python: >=3.9
License-File: LICENSE.txt
Requires-Dist: PyYAML ==6.0.1
Requires-Dist: gdown
Requires-Dist: joblib
Requires-Dist: lightgbm ==4.3.0
Requires-Dist: numpy
Requires-Dist: pathlib
Requires-Dist: python-box ==7.1.1
Requires-Dist: scikit-learn ==1.4.0
Requires-Dist: sentencepiece ==0.2.0
Requires-Dist: setuptools
Requires-Dist: torch
Requires-Dist: torchaudio
Requires-Dist: torchvision
Requires-Dist: tqdm
Requires-Dist: transformers ==4.38.2
Requires-Dist: types-PyYAML ==6.0.12.12
Requires-Dist: wheel
